prompting_forge/__init__.py
prompting_forge/prompting/__init__.py
prompting_forge/prompting/prompt.py
prompting_forge/versioning.py
prompting_forge-0.2.1.dist-info/METADATA
prompting_forge-0.2.1.dist-info/WHEEL
prompting_forge-0.2.1.dist-info/licenses/LICENSE
prompting_forge-0.2.1.dist-info/RECORD
