Metadata-Version: 2.4
Name: prompting-forge
Version: 0.2.1
Summary: A lightweight, modular library for building, composing, and managing structured prompts for LLMs
License-File: LICENSE
Requires-Python: >=3.10,<4.0
Classifier: Programming Language :: Python :: 3
Classifier: Programming Language :: Python :: 3.10
Classifier: Programming Language :: Python :: 3.11
Classifier: Programming Language :: Python :: 3.12
Classifier: Programming Language :: Python :: 3.13
Classifier: Programming Language :: Python :: 3.14
Requires-Dist: genai-forge (>=0.2.3)
